p6plab_datasage/__init__.py
p6plab_datasage/config.py
p6plab_datasage/server.py
p6plab_datasage/tools/__init__.py
p6plab_datasage/tools/children.py
p6plab_datasage/tools/get_page.py
p6plab_datasage/tools/search.py
p6plab_datasage/utils/__init__.py
p6plab_datasage/utils/file_utils.py
p6plab_datasage/utils/graceful_exit.py
p6plab_datasage/utils/resource_manager.py
p6plab_datasage/utils/search_engine.py
p6plab_datasage/utils/security.py
p6plab_datasage-1.0.3.dist-info/METADATA
p6plab_datasage-1.0.3.dist-info/WHEEL
p6plab_datasage-1.0.3.dist-info/entry_points.txt
p6plab_datasage-1.0.3.dist-info/licenses/LICENSE
p6plab_datasage-1.0.3.dist-info/RECORD
