Metadata-Version: 2.4
Name: p6plab-datasage
Version: 1.0.3
Summary: MCP server for secure local file system access
Project-URL: Homepage, https://github.com/p6plab/datasage
Project-URL: Repository, https://github.com/p6plab/datasage
Project-URL: Issues, https://github.com/p6plab/datasage/issues
Author-email: P6P Lab <contact@p6plab.com>
License: MIT License
License-File: LICENSE
Classifier: Development Status :: 4 - Beta
Classifier: Intended Audience :: Developers
Classifier: License :: OSI Approved :: MIT License
Classifier: Programming Language :: Python :: 3
Classifier: Programming Language :: Python :: 3.10
Classifier: Programming Language :: Python :: 3.11
Classifier: Programming Language :: Python :: 3.12
Requires-Python: >=3.10
Requires-Dist: fastmcp>=2.0.0
Requires-Dist: pyyaml>=6.0
Requires-Dist: sentence-transformers>=5.0.0
Provides-Extra: dev
Requires-Dist: black>=23.0.0; extra == 'dev'
Requires-Dist: pytest-cov>=4.0.0; extra == 'dev'
Requires-Dist: pytest-xdist>=3.0.0; extra == 'dev'
Requires-Dist: pytest>=7.0.0; extra == 'dev'
Requires-Dist: ruff>=0.1.0; extra == 'dev'
